dropzone/__init__.py
dropzone/client.py
dropzone/exceptions.py
dropzone/py.typed
dropzone/resources.py
dropzone_py-1.0.5.dist-info/METADATA
dropzone_py-1.0.5.dist-info/WHEEL
dropzone_py-1.0.5.dist-info/licenses/LICENSE.md
dropzone_py-1.0.5.dist-info/RECORD
