Metadata-Version: 2.4
Name: dropzone-py
Version: 1.0.5
Summary: This is a simple wrapper for the DropZone.ai API
Project-URL: Homepage, https://github.com/netlink-cpaton/PyZone
Project-URL: Issues, https://github.com/you/your-repo/issues
Project-URL: Documentation, https://github.com/netlink-cpaton/PyZone/blob/main/README.md
Author-email: Cameron Paton <cpaton@netlink.com.au>
License: MIT License
License-File: LICENSE.md
Requires-Python: >=3.12
Requires-Dist: httpx>=0.28.1
Requires-Dist: pydantic>=2.11.7
